melfapy/Melfa.py
melfapy/__init__.py
melfapy/utils/__init__.py
melfapy/utils/advanced_S_curve_acceleration.py
melfapy-0.1.0.dist-info/METADATA
melfapy-0.1.0.dist-info/WHEEL
melfapy-0.1.0.dist-info/top_level.txt
melfapy-0.1.0.dist-info/RECORD
