Metadata-Version: 2.4
Name: melfapy
Version: 0.1.0
Summary: Python library for controlling Mitsubishi MELFA robots
Requires-Python: >=3.11
Requires-Dist: numpy>=2.3.1
